README.md
setup.py
simple_memory_testing_env/__init__.py
simple_memory_testing_env.egg-info/PKG-INFO
simple_memory_testing_env.egg-info/SOURCES.txt
simple_memory_testing_env.egg-info/dependency_links.txt
simple_memory_testing_env.egg-info/not-zip-safe
simple_memory_testing_env.egg-info/requires.txt
simple_memory_testing_env.egg-info/top_level.txt
simple_memory_testing_env/env/__init__.py
simple_memory_testing_env/env/simple_memory_testing_env.py