Metadata-Version: 2.1
Name: simple-memory-testing-env
Version: 0.0.1
Summary: OpenAI Gym-compatible implementation of a simple memory-testing environment.
Home-page: https://github.com/Near32/SimpleMemoryTestingEnv
License: UNKNOWN
Platform: UNKNOWN
Classifier: Intended Audience :: Developers
Classifier: Topic :: Scientific/Engineering :: Artificial Intelligence 
Classifier: Programming Language :: Python :: 3
Requires-Python: >=3.6
